batch_img/__init__.py
batch_img/auto.py
batch_img/border.py
batch_img/common.py
batch_img/config.json
batch_img/const.py
batch_img/do_effect.py
batch_img/effect.py
batch_img/interface.py
batch_img/log.py
batch_img/main.py
batch_img/no_gps.py
batch_img/orientation.py
batch_img/remove_bg.py
batch_img/resize.py
batch_img/rotate.py
batch_img/transparent.py
batch_img-0.3.5.dist-info/licenses/LICENSE
batch_img-0.3.5.dist-info/METADATA
batch_img-0.3.5.dist-info/WHEEL
batch_img-0.3.5.dist-info/entry_points.txt
batch_img-0.3.5.dist-info/top_level.txt
batch_img-0.3.5.dist-info/RECORD
