Metadata-Version: 2.4
Name: batch_img
Version: 0.3.5
Summary: Batch process (resize, rotate, remove background, remove GPS, add border, set transparency, auto do all) image files (HEIC, JPG, PNG)
Author-email: John Liu <rim2rim@gmail.com>
License-Expression: MIT
Project-URL: Download, https://pypi.org/project/batch-img/
Project-URL: Homepage, https://github.com/john-liu2/batch_img
Keywords: cli-tool,image-processing,batch-processing,special-effect,remove-background,remove-gps,resize-image,rotate-image
Classifier: Development Status :: 5 - Production/Stable
Classifier: Intended Audience :: End Users/Desktop
Classifier: Operating System :: OS Independent
Classifier: Programming Language :: Python :: 3.12
Classifier: Programming Language :: Python :: 3.13
Classifier: Programming Language :: Python :: 3.14
Classifier: Programming Language :: Python :: 3 :: Only
Classifier: Topic :: Utilities
Requires-Python: >=3.12
License-File: LICENSE
Requires-Dist: click
Requires-Dist: httpx
Requires-Dist: loguru
Requires-Dist: numpy
Requires-Dist: onnxruntime
Requires-Dist: opencv-python
Requires-Dist: packaging
Requires-Dist: piexif
Requires-Dist: pillow
Requires-Dist: pillow-heif
Requires-Dist: rembg
Requires-Dist: tqdm
Dynamic: license-file
